czpeedy/__init__.py
czpeedy/czpeedy.py
czpeedy/parameter_space.py
czpeedy/runner.py
czpeedy/trial_parameters.py
czpeedy-0.2.3.dist-info/METADATA
czpeedy-0.2.3.dist-info/WHEEL
czpeedy-0.2.3.dist-info/entry_points.txt
czpeedy-0.2.3.dist-info/licenses/LICENSE
czpeedy-0.2.3.dist-info/RECORD
