Metadata-Version: 2.3
Name: czpeedy
Version: 0.2.3
Summary: A command-line tool used to determine the tensorstore settings which yield the fastest write speed on a given machine.
Project-URL: Homepage, https://github.com/royerlab/czpeedy
Project-URL: Issues, https://github.com/royerlab/czpeedy/issues
Author-email: Seth Hinz <sethhinz@me.com>
License-File: LICENSE
Classifier: License :: OSI Approved :: MIT License
Classifier: Operating System :: OS Independent
Classifier: Programming Language :: Python :: 3
Requires-Python: >=3.12
Requires-Dist: numpy>=2.0.0
Requires-Dist: ruff>=0.5.3
Requires-Dist: tensorstore>=0.1.63
Requires-Dist: termcolor>=2.4.0
